durations_nlp/__init__.py
durations_nlp/constants.py
durations_nlp/duration.py
durations_nlp/exceptions.py
durations_nlp/helpers.py
durations_nlp/parser.py
durations_nlp/scales.py
durations_nlp-1.0.1.dist-info/LICENSE
durations_nlp-1.0.1.dist-info/WHEEL
durations_nlp-1.0.1.dist-info/METADATA
durations_nlp-1.0.1.dist-info/RECORD
