Metadata-Version: 2.1
Name: durations-nlp
Version: 1.0.1
Summary: A python durations parsing library.
Home-page: https://github.com/timwedde/durations_nlp
License: MIT
Author: Tim Wedde
Author-email: timwedde@icloud.com
Requires-Python: >=3.6,<4.0
Classifier: License :: OSI Approved :: MIT License
Classifier: Programming Language :: Python :: 3
Classifier: Programming Language :: Python :: 3.6
Classifier: Programming Language :: Python :: 3.7
Classifier: Programming Language :: Python :: 3.8
Project-URL: Repository, https://github.com/timwedde/durations_nlp
